{
    "time": {
        "cpu_time_user": "00:00:00.760",
        "cpu_time_system": "00:00:00.190",
        "runtime": "00:00:01.706",
        "cpu_time_iowait": "00:00:00.000"
    },
    "peak_resources": {
        "cpu_percent": 109.6,
        "memory_rss": "173MiB",
        "memory_vms": "310MiB",
        "threads": 2
    },
    "avg_resources": {
        "cpu_percent": 49.799999999999976,
        "memory_rss": "136MiB",
        "memory_vms": "251MiB",
        "threads": 1.7894736842105263
    }
}